[{"authors":["admin"],"categories":null,"content":"Brian is a ipsum dolor sit amet, consectetur adipiscing elit. Sed neque elit, tristique placerat feugiat ac, facilisis vitae arcu. Proin eget egestas augue. Praesent ut sem nec arcu pellentesque aliquet. Duis dapibus diam vel metus tempus vulputate.\nLorem ipsum dolor sit amet, consectetur adipiscing elit. Sed neque elit, tristique placerat feugiat ac, facilisis vitae arcu. Proin eget egestas augue. Praesent ut sem nec arcu pellentesque aliquet. Duis dapibus diam vel metus tempus vulputate.\n","date":-62135596800,"expirydate":-62135596800,"kind":"term","lang":"en","lastmod":-62135596800,"objectID":"2525497d367e79493fd32b198b28f040","permalink":"/author/brian-d.-frost/","publishdate":"0001-01-01T00:00:00Z","relpermalink":"/author/brian-d.-frost/","section":"authors","summary":"Brian is a ipsum dolor sit amet, consectetur adipiscing elit. Sed neque elit, tristique placerat feugiat ac, facilisis vitae arcu. Proin eget egestas augue. Praesent ut sem nec arcu pellentesque aliquet.","tags":null,"title":"Brian D. Frost","type":"authors"}]